piicloak/__init__.py
piicloak/__main__.py
piicloak/api.py
piicloak/app.py
piicloak/config.py
piicloak/engine.py
piicloak/metrics.py
piicloak/middleware.py
piicloak/recognizers.py
piicloak-1.0.4.dist-info/licenses/LICENSE
piicloak-1.0.4.dist-info/METADATA
piicloak-1.0.4.dist-info/WHEEL
piicloak-1.0.4.dist-info/entry_points.txt
piicloak-1.0.4.dist-info/top_level.txt
piicloak-1.0.4.dist-info/RECORD
