Metadata-Version: 2.4
Name: piicloak
Version: 1.0.4
Summary: Enterprise-grade PII detection and anonymization API. Helps achieve GDPR/CCPA compliance. Supports 31 entity types.
Home-page: https://github.com/dimanjet/piicloak
Author: Dmitry Marinov
Author-email: Dmitry Marinov <marinovdk@gmail.com>
License: MIT
Project-URL: Homepage, https://github.com/dimanjet/piicloak
Project-URL: Documentation, https://github.com/dimanjet/piicloak#readme
Project-URL: Repository, https://github.com/dimanjet/piicloak
Project-URL: Issues, https://github.com/dimanjet/piicloak/issues
Project-URL: Changelog, https://github.com/dimanjet/piicloak/blob/main/CHANGELOG.md
Keywords: pii,pii-detection,anonymization,gdpr,ccpa,hipaa,privacy,data-protection,presidio,spacy,nlp,ner,salesforce,legal-tech,fintech,healthcare,text-processing,redaction,compliance
Classifier: Development Status :: 5 - Production/Stable
Classifier: Intended Audience :: Developers
Classifier: Intended Audience :: Information Technology
Classifier: Intended Audience :: Legal Industry
Classifier: Intended Audience :: Healthcare Industry
Classifier: Intended Audience :: Financial and Insurance Industry
Classifier: License :: OSI Approved :: MIT License
Classifier: Programming Language :: Python :: 3
Classifier: Programming Language :: Python :: 3.9
Classifier: Programming Language :: Python :: 3.10
Classifier: Programming Language :: Python :: 3.11
Classifier: Programming Language :: Python :: 3.12
Classifier: Topic :: Security
Classifier: Topic :: Text Processing
Classifier: Environment :: Web Environment
Classifier: Framework :: Flask
Requires-Python: >=3.9
License-File: LICENSE
Requires-Dist: flask>=3.0.0
Requires-Dist: presidio-analyzer>=2.2.0
Requires-Dist: presidio-anonymizer>=2.2.0
Requires-Dist: spacy>=3.7.0
Requires-Dist: python-docx>=1.0.0
Provides-Extra: dev
Requires-Dist: pytest>=7.0.0; extra == "dev"
Requires-Dist: pytest-cov>=4.0.0; extra == "dev"
Requires-Dist: black>=23.0.0; extra == "dev"
Requires-Dist: flake8>=6.0.0; extra == "dev"
Requires-Dist: mypy>=1.0.0; extra == "dev"
Provides-Extra: production
Requires-Dist: gunicorn>=21.0.0; extra == "production"
Dynamic: author
Dynamic: home-page
Dynamic: license-file
Dynamic: requires-python
